setup.py
wenjiaocao/__init__.py
wenjiaocao/who.py
wenjiaocao.egg-info/PKG-INFO
wenjiaocao.egg-info/SOURCES.txt
wenjiaocao.egg-info/dependency_links.txt
wenjiaocao.egg-info/not-zip-safe
wenjiaocao.egg-info/top_level.txt