Metadata-Version: 1.0
Name: wenjiaocao
Version: 0.1
Summary: who is she
Home-page: http://www.caixin.com/
Author: qianlong.yang
Author-email: 626568549@qq.com
License: MIT
Platform: UNKNOWN
